Workbook

Sheet Controls
A1: Parameter | B1: Value | C1: Notes
A2: Default Transaction Fee | B2: 0.07 | C2: Used in revenue model
A3: Featured Listing Fee | B3: 150000 | C3: Average monthly fee per featured listing
A4: Verification Fee | B4: 200000 | C4: Advanced verification price
A5: Buyer Subscription Fee | B5: 100000 | C5: Monthly average subscription fee
A6: Target Monthly Listings | B6: 1000 | C6: Control assumption
A7: Target Deal Conversion Rate | B7: 0.03 | C7: Deals / active listings
A8: Avg Deal Value | B8: 5000000 | C8: Average transaction size
A9: Verification Window Days | B9: 3 | C9: Standard buyer review period

Sheet README
A1: Sheet | B1: Purpose
A2: Controls | B2: Editable assumptions used across revenue model and KPI dashboard
A3: Asset_Catalog | B3: 300 asset categories/types that Msell can list
A4: Sellers | B4: Seller CRM and status tracking
A5: Buyers | B5: Buyer CRM and demand profile
A6: Outreach_Leads | B6: Lead generation and outreach pipeline
A7: Listings | B7: Active and draft asset listings
A8: Verification | B8: Ownership / metrics / revenue verification tracker
A9: Deals | B9: Deal room pipeline and commercial status
A10: Transfer_Checklists | B10: Operational transfer tasks by deal and platform
A11: Escrow | B11: Escrow state tracker
A12: Marketing_Calendar | B12: Campaign execution tracker
... A17: Admin_Ops | B17: Internal queue / moderation / incident tracker

Sheet Asset_Catalog
A1: Asset_ID | B1: Category | C1: Asset_Type | D1: Status | E1: Verification_Required | F1: Transfer_Template
A2: 1 | B2: Community Platform | C2: Discord Server | D2: Active | E2: Required | F2: Template Available
A3: 2 | B3: Community Platform | C3: Telegram Channel | D3: Active | E3: Required | F3: Template Available
A4: 3 | B4: Community Platform | C4: Telegram Group | D4: Active | E4: Required | F4: Template Available
A5: 4 | B5: Community Platform | C5: Naver Cafe | D5: Active | E5: Required | F5: Template Available
A6: 5 | B6: Community Platform | C6: KakaoTalk Open Chat | D6: Active | E6: Required | F6: Template Available
A7: 6 | B7: Community Platform | C7: KakaoTalk Channel | D7: Active | E7: Required | F7: Template Available
A8: 7 | B8: Community Platform | C8: Facebook Group | D8: Active | E8: Required | F8: Template Available
A9: 8 | B9: Community Platform | C9: Reddit Subreddit | D9: Active | E9: Required | F9: Template Available
A10: 9 | B10: Community Platform | C10: Slack Community | D10: Active | E10: Required | F10: Template Available
A11: 10 | B11: Community Platform | C11: Guilded Server | D11: Active | E11: Required | F11: Template Available
A12: 11 | B12: Community Platform | C12: Line OpenChat | D12: Active | E12: Required | F12: Template Available
A13: 12 | B13: Community Platform | C13: WhatsApp Community | D13: Active | E13: Required | F13: Template Available
... A301: 90 | B301: Ads / Traffic Network | C301: Digital Promotion Network | D301: Active | E301: Required | F301: Template Available

Sheet Sellers
A1: Seller_ID | B1: Seller_Name | C1: Primary_Asset_Type | D1: Status | E1: Verification_Status | F1: Last_Contact_Date | G1: Risk_Level
A2: 1 | B2: Alpha Media | C2: Telegram / Discord | D2: active | E2: Basic Verified | F2: 2026-03-01 | G2: High
A3: 2 | B3: Cafe Labs | C3: Naver Cafe | D3: active | E3: Ownership Verified | F3: 2026-03-02 | G3: Medium
A4: 3 | B4: Growth Studio | C4: YouTube / Newsletter | D4: pipeline | E4: Pending | F4: 2026-03-03 | G4: Medium
A5: 4 | B5: Creator Holdings | C5: Instagram / Website | D5: active | E5: Full Verified | F5: 2026-03-04 | G5: Low
A6: 5 | B6: Community Ops | C6: Discord | D6: inactive | E6: Rejected | F6: 2026-03-05 | G6: High

Sheet Buyers
A1: Buyer_ID | B1: Buyer_Name | C1: Preferred_Assets | D1: Budget_Range | E1: Niche | F1: Status | G1: Last_Contact_Date
A2: 1 | B2: Creator Investor Fund | C2: Telegram / Discord | D2: ₩5M-₩30M | E2: Crypto / Community | F2: active | G2: 2026-03-01
A3: 2 | B3: Media Rollup Co | C3: Website / Newsletter | D3: ₩30M-₩300M | E3: Media / SEO | F3: active | G3: 2026-03-02
A4: 3 | B4: Growth Operator | C4: Instagram / YouTube | D4: ₩3M-₩20M | E4: Creator assets | F4: pipeline | G4: 2026-03-03

Sheet Outreach_Leads
A1: Lead_ID | B1: Platform | C1: Asset_Name | D1: URL | E1: Contact_Method | F1: Pipeline_Status | G1: Last_Action_Date | H1: Notes
A2: 1 | B2: Telegram | C2: CryptoAlpha | D2: https://t.me/example1 | E2: DM | F2: new | G2: 2026-03-01 | H2: Owner contacted
A3: 2 | B3: Discord | C3: Gaming Hub | D3: https://discord.gg/example2 | E3: Email | F3: follow_up | G3: 2026-03-02 | H3: Interested in valuation
A4: 3 | B4: Naver Cafe | C4: Growth Cafe | D4: https://cafe.naver.com/example3 | E4: DM | F4: qualified | G4: 2026-03-03 | H4: Needs onboarding
A5: 4 | B5: YouTube | C5: TechReview KR | D5: https://youtube.com/example4 | E5: Email | F5: closed_won | G5: 2026-03-04 | H5: Listing created

Sheet Listings
A1: Listing_ID | B1: Seller_ID | C1: Asset_ID | D1: Platform | E1: Niche | F1: Listing_Status | G1: Subscribers_Members | H1: Avg_Reach | I1: Monthly_Revenue | J1: Asking_Price | K1: Verification_Status
A2: 101 | B2: 1 | C2: 1002 | D2: Telegram Channel | E2: Crypto | F2: active | G2: 12000 | H2: 3000 | I2: 2500000 | J2: 15000000 | K2: verified_basic
A3: 102 | B3: 2 | C3: 1004 | D3: Naver Cafe | E3: Business | F3: active | G3: 35000 | H3: 5000 | I3: 4000000 | J3: 30000000 | K3: verified_ownership
A4: 103 | B4: 4 | C4: 1031 | D4: Instagram Account | E4: Travel | F4: draft | G4: 22000 | H4: 2000 | I4: 1200000 | J4: 9000000 | K4: pending
A5: 104 | B5: 3 | C5: 1071 | D5: YouTube Channel | E5: Tech | F5: active | G5: 54000 | H5: 15000 | I5: 8000000 | J5: 45000000 | K5: verified_full
A6: 105 | B6: 1 | C6: 1001 | D6: Discord Server | E6: Gaming | F6: sold | G6: 8000 | H6: 1800 | I6: 900000 | J6: 7000000 | K6: verified_basic

Sheet Verification
A1: Verification_ID | B1: Listing_ID | C1: Check_Type | D1: Result | E1: Evidence_Summary | F1: Checked_Date | G1: Checked_By
A2: 201 | B2: 101 | C2: ownership | D2: pass | E2: Owner screenshot uploaded | F2: 2026-03-01 | G2: Ops 1
A3: 202 | B3: 101 | C3: metrics | D3: pass | E3: Telegram views aligned | F3: 2026-03-01 | G3: Ops 2
A4: 203 | B4: 102 | C4: ownership | D4: pass | E4: Manager rights verified | F4: 2026-03-02 | G4: Ops 1
A5: 204 | B5: 104 | C5: revenue | D5: review | E5: Need updated payout screenshot | F5: 2026-03-03 | G5: Ops 3

Sheet Deals
A1: Deal_ID | B1: Listing_ID | C1: Seller_ID | D1: Buyer_ID | E1: Deal_Stage | F1: Agreed_Price | G1: Opened_Date | H1: Target_Close_Date | I1: Health
A2: 301 | B2: 101 | C2: 1 | D2: 1 | E2: offer_submitted | F2: 13000000 | G2: 2026-03-01 | H2: 2026-03-08 | I2: pending
A3: 302 | B3: 102 | C3: 2 | D3: 2 | E3: escrow_funded | F3: 28500000 | G3: 2026-03-02 | H3: 2026-03-10 | I3: green
A4: 303 | B4: 104 | C4: 3 | D4: 3 | E4: verification_window | F4: 42000000 | G4: 2026-03-03 | H4: 2026-03-12 | I4: amber

Sheet Transfer_Checklists
A1: Task_ID | B1: Deal_ID | C1: Platform | D1: Task_Description | E1: Task_Status | F1: Due_Date
A2: 401 | B2: 302 | C2: Naver Cafe | D2: Buyer added as staff | E2: done | F2: 2026-03-02
A3: 402 | B3: 302 | C3: Naver Cafe | D3: Manager role transferred | E3: in_progress | F3: 2026-03-03
A4: 403 | B4: 303 | C4: YouTube | D4: Buyer invited to Brand Account | E4: done | F4: 2026-03-03
A5: 404 | B5: 303 | C5: YouTube | D5: Primary owner wait period completed | E5: pending | F5: 2026-03-10

Sheet Escrow
A1: Escrow_ID | B1: Deal_ID | C1: Escrow_Amount | D1: Escrow_Status | E1: Funded_Date | F1: Release_Date | G1: Notes
A2: 501 | B2: 302 | C2: 28500000 | D2: funded | E2: 2026-03-02 | F2: 2026-03-10 | G2: Platform escrow
A3: 502 | B3: 303 | C3: 42000000 | D3: pending_release | E3: 2026-03-03 | F3: 2026-03-12 | G3: Buyer confirmation pending

Sheet Marketing_Calendar
A1: Campaign_ID | B1: Channel | C1: Content_Title | D1: Publish_Date | E1: Status | F1: Objective | G1: Source_Type
A2: 601 | B2: SEO | C2: How to sell a Telegram channel | D2: 2026-03-07 | E2: planned | F2: Seller acquisition | G2: Organic
A3: 602 | B3: YouTube | C3: Discord server valuation guide | D3: 2026-03-08 | E3: draft | F3: Seller acquisition | G3: Organic
A4: 603 | B4: Telegram | C4: Featured listings weekly digest | D4: 2026-03-09 | E4: scheduled | F4: Buyer activation | G4: Owned
A5: 604 | B5: Partnership | C5: Creator community outreach | D5: 2026-03-10 | E5: active | F5: Supply growth | G5: Partner

Sheet AI_Pipeline
A1: AI_Run_ID | B1: Stage | C1: Asset_Group | D1: Output | E1: Status | F1: Run_Date
A2: 701 | B2: Asset Scan | C2: Telegram | D2: 100000 scanned URLs | E2: complete | F2: 2026-03-01
A3: 702 | B3: Scoring | C3: All | D3: 20000 qualified prospects | E3: complete | F3: 2026-03-02
A4: 703 | B4: Outreach | C4: Telegram / Discord | D4: 2000 responses | E4: active | F4: 2026-03-03
A5: 704 | B5: Listing Gen | C5: All | D5: 1000 drafted listings | E5: active | F5: 2026-03-04

Sheet Revenue_Model
A1: Metric | B1: Formula / Input | C1: Monthly
A2: Active Listings | B2: Input / KPI Link | C2: =KPI_Dashboard!B3 -> 300
A3: Deal Conversion Rate | B3: Control | C3: ='Controls'!B6 -> 1000
A4: Completed Deals | B4: Formula | C4: =C2*C3 -> 300000
A5: Avg Deal Value | B5: Control | C5: ='Controls'!B7 -> 0.03
A6: GMV | B6: Formula | C6: =C4*C5 -> 9000
A7: Transaction Fee % | B7: Control | C7: ='Controls'!B2 -> 0.07
A8: Transaction Fee Revenue | B8: Formula | C8: =C6*C7 -> 630
A9: Featured Listing Count | B9: Input | C9: 50
A10: Featured Listing Fee | B10: Control | C10: ='Controls'!B3 -> 150000
A11: Featured Revenue | B11: Formula | C11: =C9*C10 -> 7500000
A12: Verification Orders | B12: Input | C12: 20
A13: Verification Fee | B13: Control | C13: ='Controls'!B4 -> 200000
A14: Verification Revenue | B14: Formula | C14: =C12*C13 -> 4000000
A15: Buyer Subscribers | B15: Input | C15: 15
A16: Buyer Subscription Fee | B16: Control | C16: ='Controls'!B5 -> 100000
A17: Subscription Revenue | B17: Formula | C17: =C15*C16 -> 1500000
A18: Total Monthly Revenue | B18: Formula | C18: =SUM(C8,C11,C14,C17) -> 13000630

Sheet KPI_Dashboard
A1: Msell KPI Dashboard
A2: Metric | B2: Value | C2: Target | D2: Notes
A3: Total Asset Types | B3: =COUNTA(Asset_Catalog!A:A)-1 -> 300 | C3: 300 | D3: Catalog depth
A4: Active Listings | B4: =COUNTIF(Listings!F:F,"active") -> 3 | C4: 1000 | D4: Supply
A5: Sold Listings | B5: =COUNTIF(Listings!F:F,"sold") -> 1 | C5: 30 | D5: Completed exits
A6: Open Deals | B6: =COUNTA(Deals!A:A)-1 -> 3 | C6: 20 | D6: Current pipeline
A7: Escrow Funded Deals | B7: =COUNTIF(Escrow!D:D,"funded") -> 1 | C7: 10 | D7: Trust metric
A8: Verified Listings | B8: =COUNTIF(Listings!K:K,"verified_full")+COUNTIF(Listings!K:K,"verified_ownership")+COUNTIF(Listings!K:K,"verified_basic") -> 4 | C8: 300 | D8: Quality supply
A9: Total Asking Value | B9: =SUM(Listings!J:J) -> 106000000 | C9: 500000000 | D9: Inventory value
A10: Monthly Revenue | B10: ='Revenue_Model'!C18 -> 13000630 | C10: 15000000 | D10: Model output

Sheet Risk_Log
A1: Risk_ID | B1: Risk_Type | C1: Scope | D1: Severity | E1: Mitigation | F1: Status | G1: Owner
A2: 801 | B2: Fraud | C2: Seller | D2: High | E2: Escrow mandatory for deals > threshold | F2: open | G2: Ops Lead
A3: 802 | B3: Account Reclaim | C3: Platform | D3: High | E3: Transfer checklist + verification window | F3: monitoring | G3: Ops Lead
A4: 803 | B4: Fake Metrics | C4: Listing | D4: Medium | E4: Admin proof + analytics review | F4: open | G4: Verification Team
A5: 804 | B5: Policy Violation | C5: Platform | D5: High | E5: Restricted asset policy + manual review | F5: open | G5: Admin

Sheet Admin_Ops
A1: Ticket_ID | B1: Queue | C1: Reference_ID | D1: Priority | E1: Status | F1: Action_Note
A2: 901 | B2: Listing Review | C2: 101 | D2: high | E2: pending | F2: Check ownership proof
A3: 902 | B3: Dispute Review | C3: 302 | D3: high | E3: active | F3: Buyer requests refund
A4: 903 | B4: Escalation | C4: 303 | D4: medium | E4: open | F4: Need updated revenue proof
A5: 904 | B5: Fraud Flag | C5: 105 | D5: high | E5: closed | F5: False positive after review
